kafkaplus.py
kafkaplus-0.0.1.dist-info/METADATA
kafkaplus-0.0.1.dist-info/WHEEL
kafkaplus-0.0.1.dist-info/entry_points.txt
kafkaplus-0.0.1.dist-info/top_level.txt
kafkaplus-0.0.1.dist-info/RECORD
